wolk.py
wolk-0.10.0.dist-info/LICENSE
wolk-0.10.0.dist-info/METADATA
wolk-0.10.0.dist-info/WHEEL
wolk-0.10.0.dist-info/top_level.txt
wolk-0.10.0.dist-info/RECORD
